LICENSE.txt
MANIFEST.in
README.txt
setup.cfg
setup.py
doc/calibration_window.png
doc/conf.py
doc/download.txt
doc/index.txt
doc/main_window.png
doc/report.png
doc/screenshots.txt
doc/_static/favicon.ico
doc/_static/logo.png
doc/_templates/layout.html
doc/_templates/sidebar.html
doc/devel/canvas.txt
doc/devel/index.txt
doc/devel/report.txt
doc/devel/tm1.txt
doc/devel/wheel.txt
doc/devel/wheelwright.txt
doc/guide/acknowledgments.txt
doc/guide/calibration.png
doc/guide/credits.txt
doc/guide/howto.txt
doc/guide/index.txt
doc/guide/install.txt
doc/guide/intro.txt
doc/guide/license.txt
doc/guide/report.pdf
doc/guide/tension_plot.png
doc/guide/wheelwright.cfg
doc/guide/wheelwright1.png
doc/guide/wheelwright2.png
icons/wheelwright.icns
tests/__init__.py
tests/test_tm1.py
wheelwright/__init__.py
wheelwright/canvas.py
wheelwright/report.py
wheelwright/tm1.py
wheelwright/wheel.py
wheelwright/wheelwright.py
wheelwright.egg-info/PKG-INFO
wheelwright.egg-info/SOURCES.txt
wheelwright.egg-info/dependency_links.txt
wheelwright.egg-info/entry_points.txt
wheelwright.egg-info/not-zip-safe
wheelwright.egg-info/requires.txt
wheelwright.egg-info/top_level.txt