Metadata-Version: 1.0
Name: wheelwright
Version: 0.1.3
Summary: Bicycle wheel tension visualizer
Home-page: http://biciworks.com/wheelwright/
Author: Kris Andersen
Author-email: kris@biciworks.com
License: GPLv3
Platform: any
Classifier: Development Status :: 3 - Alpha
Classifier: Environment :: MacOS X
Classifier: Environment :: X11 Applications
Classifier: Environment :: Win32 (MS Windows)
Classifier: Intended Audience :: End Users/Desktop
Classifier: Intended Audience :: Science/Research
Classifier: Natural Language :: English
Classifier: License :: OSI Approved :: GNU General Public License (GPL)
Classifier: Operating System :: OS Independent
Classifier: Programming Language :: Python
Classifier: Topic :: Education
Classifier: Topic :: Scientific/Engineering
